aws_secrets/__init__.py
aws_secrets/cli/__init__.py
aws_secrets/cli/cli.py
aws_secrets/cli/decrypt.py
aws_secrets/cli/deploy.py
aws_secrets/cli/encrypt.py
aws_secrets/cli/set_parameter.py
aws_secrets/cli/set_secret.py
aws_secrets/cli/version.py
aws_secrets/cli/view_parameter.py
aws_secrets/cli/view_secret.py
aws_secrets/config/__init__.py
aws_secrets/config/config_reader.py
aws_secrets/config/providers/__init__.py
aws_secrets/config/providers/secretsmanager/__init__.py
aws_secrets/config/providers/secretsmanager/entry.py
aws_secrets/config/providers/secretsmanager/provider.py
aws_secrets/config/providers/ssm/__init__.py
aws_secrets/config/providers/ssm/entry.py
aws_secrets/config/providers/ssm/provider.py
aws_secrets/helpers/__init__.py
aws_secrets/helpers/catch_exceptions.py
aws_secrets/helpers/logging.py
aws_secrets/miscellaneous/__init__.py
aws_secrets/miscellaneous/cloudformation.py
aws_secrets/miscellaneous/crypto.py
aws_secrets/miscellaneous/kms.py
aws_secrets/miscellaneous/prompt.py
aws_secrets/miscellaneous/session.py
aws_secrets/miscellaneous/utils.py
aws_secrets/representers/__init__.py
aws_secrets/representers/literal.py
aws_secrets/tags/__init__.py
aws_secrets/tags/cmd.py
aws_secrets/tags/file.py
aws_secrets/tags/output_stack.py
aws_secrets/yaml.py
aws_ssm_secrets_cli-2.6.1.dist-info/LICENSE.txt
aws_ssm_secrets_cli-2.6.1.dist-info/METADATA
aws_ssm_secrets_cli-2.6.1.dist-info/WHEEL
aws_ssm_secrets_cli-2.6.1.dist-info/entry_points.txt
aws_ssm_secrets_cli-2.6.1.dist-info/RECORD
