Metadata-Version: 2.1
Name: aws-ssm-secrets-cli
Version: 2.6.1
Summary: AWS Secret CLI for manage SSM SecureString and SecretsManager
Home-page: https://github.com/lucasvieirasilva/aws-ssm-secrets-cli
License: MIT
Keywords: AWS,SECRETS,SSM,MANAGER
Author: Lucas Vieira
Author-email: lucas.vieira94@outlook.com
Maintainer: Lucas Vieira
Maintainer-email: lucas.vieira94@outlook.com
Requires-Python: >=3.8.1,<4.0
Classifier: Intended Audience :: Developers
Classifier: License :: OSI Approved :: MIT License
Classifier: Programming Language :: Python :: 3
Classifier: Programming Language :: Python :: 3.9
Classifier: Programming Language :: Python :: 3.10
Classifier: Programming Language :: Python :: 3.11
Classifier: Programming Language :: Python :: 3.12
Requires-Dist: aws-encryption-sdk (>=3.0.0,<4.0.0)
Requires-Dist: boto3 (>=1.3,<2.0)
Requires-Dist: click (>=8.1.7,<9.0.0)
Requires-Dist: jsonschema (>=3.2.0,<4.0.0)
Requires-Dist: prompt-toolkit (>=3.0.47,<4.0.0)
Requires-Dist: ruamel-yaml (>=0.18.6,<0.19.0)
Project-URL: Repository, https://github.com/lucasvieirasilva/aws-ssm-secrets-cli
